MANIFEST.in
README.md
setup.cfg
setup.py
PixelP/PixelP.py
PixelP/__init__.py
PixelP.egg-info/PKG-INFO
PixelP.egg-info/SOURCES.txt
PixelP.egg-info/dependency_links.txt
PixelP.egg-info/requires.txt
PixelP.egg-info/top_level.txt