Metadata-Version: 2.1
Name: PixelP
Version: 0.5
Summary: Image augmeantation and preprocessing tool
Home-page: https://github.com/AnirudhVm/PixelP
Author: Anirudh VM, Tanisha Bisarya, Aarsh Ghewde, Ekansh Trivedi, Yash Sawant
Author-email: anirudh.vm63@nmims.edu.in
License: MIT
Download-URL: https://github.com/AnirudhVm/PixelP/archive/0.5.tar.gz
Keywords: Image,Augment,Reshape,Color,Gray
Platform: UNKNOWN
Classifier: Development Status :: 3 - Alpha
Classifier: Intended Audience :: Developers
Classifier: Topic :: Software Development :: Build Tools
Classifier: License :: OSI Approved :: MIT License
Classifier: Programming Language :: Python :: 3
Classifier: Programming Language :: Python :: 3.4
Classifier: Programming Language :: Python :: 3.5
Classifier: Programming Language :: Python :: 3.6
